icschedule/__init__.py
icschedule/main.py
icschedule/py.typed
icschedule/scheduler.py
icschedule/db/__init__.py
icschedule/db/db_interface.py
icschedule/models/__init__.py
icschedule/models/fields.py
icschedule/models/model.py
icschedule/models/queue.py
icschedule/models/resource.py
icschedule/models/task.py
icschedule/models/user.py
icschedule/schedulers/__init__.py
icschedule/schedulers/slurm.py
icschedule/schedulers/slurm_parser.py
icschedule-0.0.2.dist-info/LICENSE
icschedule-0.0.2.dist-info/METADATA
icschedule-0.0.2.dist-info/WHEEL
icschedule-0.0.2.dist-info/top_level.txt
icschedule-0.0.2.dist-info/RECORD
